{
  "ExternalData": [
    {
      "KC_0": {
        "questionsData": {
          "questions_1": {
            "qusType": "MCSS",
            "pageNo": "17",
            "question": "At idle, the engine speed is controlled by which component, when the PLA is in the idle position?",
            "Options": [
              "T2C sensor",
              "Idle speed lever",
              "Ground idle adjustment screw",
              "Idle floor stop"
            ],
            "correctAnswer": "1",
            "imagePath": "",
            "Shuffle": "false",
            "correctFeedback": "<p><strong>That's Correct!</strong></p><p> You have chosen the correct option.</p>",
            "InCorrectFeedback": "<p><strong>That's Incorrect!</strong></p><p>You have chosen the wrong option. The valid answer is &quot;T2C sensor&quot;</p>",
            "partialFeedback": "<p><strong>That's Incorrect!</strong></p><p>The valid answer is &quot;T2C sensor&quot;</p>",
            "FirstInCorrectFeedback": "<p><strong>That's Incorrect!</strong></p><p>You have chosen the wrong option. Please try again.</p>"
          }
        }
      }
    }
  ]
}